oidcmsg/__init__.py
oidcmsg/configure.py
oidcmsg/constant.py
oidcmsg/context.py
oidcmsg/exception.py
oidcmsg/impexp.py
oidcmsg/item.py
oidcmsg/logging.py
oidcmsg/message.py
oidcmsg/time_util.py
oidcmsg/util.py
oidcmsg/oauth2/__init__.py
oidcmsg/oauth2/device_authorization.py
oidcmsg/oidc/__init__.py
oidcmsg/oidc/identity_assurance.py
oidcmsg/oidc/session.py
oidcmsg/storage/__init__.py
oidcmsg/storage/abfile.py
oidcmsg-1.6.0.data/scripts/create_jwks.py
oidcmsg-1.6.0.dist-info/LICENSE
oidcmsg-1.6.0.dist-info/METADATA
oidcmsg-1.6.0.dist-info/WHEEL
oidcmsg-1.6.0.dist-info/top_level.txt
oidcmsg-1.6.0.dist-info/RECORD
