Metadata-Version: 2.1
Name: oidcmsg
Version: 1.6.0
Summary: Python implementation of OAuth2 and OpenID Connect messages
Home-page: https://github.com/IdentityPython/oidcmsg/
Author: Roland Hedberg
Author-email: roland@catalogix.se
License: Apache 2.0
Platform: UNKNOWN
Classifier: Development Status :: 4 - Beta
Classifier: License :: OSI Approved :: Apache Software License
Classifier: Programming Language :: Python :: 3.7
Classifier: Programming Language :: Python :: 3.8
Classifier: Programming Language :: Python :: 3.9
Classifier: Programming Language :: Python :: 3.10
Classifier: Topic :: Software Development :: Libraries :: Python Modules
License-File: LICENSE
